[{"pk": 1, "model": "camera.catalog", "fields": {"comment": "", "status": "o", "given": false, "working": "Y", "gift": false, "sell_price": 0, "price": 40, "who": 6, "sell_date": null, "is_borrowed": false, "camera_model": 1, "sn": "181607", "date": "2011-05-25T15:10:29", "sell_reason": ""}}, {"pk": 2, "model": "camera.catalog", "fields": {"comment": "echang\u00e9e avec une fonctionnelle lors d'une tentative de r\u00e9paration", "status": "o", "given": false, "working": "Y", "gift": false, "sell_price": 0, "price": 45, "who": 6, "sell_date": null, "is_borrowed": false, "camera_model": 2, "sn": "4900854", "date": "2011-05-25T15:10:29", "sell_reason": ""}}, {"pk": 3, "model": "camera.catalog", "fields": {"comment": "", "status": "o", "given": false, "working": "M", "gift": false, "sell_price": 0, "price": 20, "who": 6, "sell_date": null, "is_borrowed": false, "camera_model": 3, "sn": "k11660", "date": "2011-05-25T15:10:29", "sell_reason": ""}}, {"pk": 4, "model": "camera.catalog", "fields": {"comment": "Christophe MDV", "status": "o", "given": false, "working": "Y", "gift": false, "sell_price": 0, "price": 40, "who": 6, "sell_date": null, "is_borrowed": false, "camera_model": 4, "sn": "390431", "date": "2011-05-25T15:10:29", "sell_reason": ""}}, {"pk": 5, "model": "camera.catalog", "fields": {"comment": "Premier Nikon", "status": "o", "given": false, "working": "Y", "gift": false, "sell_price": 0, "price": 70, "who": 6, "sell_date": null, "is_borrowed": false, "camera_model": 5, "sn": "3157498", "date": "2011-05-25T15:10:29", "sell_reason": ""}}, {"pk": 6, "model": "camera.catalog", "fields": {"comment": "", "status": "o", "given": false, "working": "Y", "gift": false, "sell_price": 0, "price": 40, "who": 6, "sell_date": null, "is_borrowed": false, "camera_model": 6, "sn": "", "date": "2011-05-25T15:10:30", "sell_reason": ""}}, {"pk": 7, "model": "camera.catalog", "fields": {"comment": null, "status": "o", "given": false, "working": "yes", "gift": false, "sell_price": 0, "price": 30, "who": 6, "sell_date": null, "is_borrowed": false, "camera_model": 7, "sn": "", "date": "2011-05-25T15:10:30", "sell_reason": ""}}, {"pk": 8, "model": "camera.catalog", "fields": {"comment": "", "status": "o", "given": false, "working": "M", "gift": false, "sell_price": 0, "price": 10, "who": 6, "sell_date": null, "is_borrowed": false, "camera_model": 8, "sn": "594211", "date": "2011-05-25T15:10:30", "sell_reason": ""}}, {"pk": 9, "model": "camera.catalog", "fields": {"comment": null, "status": "o", "given": false, "working": "yes", "gift": false, "sell_price": 0, "price": 10, "who": 6, "sell_date": null, "is_borrowed": false, "camera_model": 9, "sn": "", "date": "2011-05-25T15:10:30", "sell_reason": ""}}, {"pk": 10, "model": "camera.catalog", "fields": {"comment": null, "status": "o", "given": false, "working": "no", "gift": false, "sell_price": 0, "price": 45, "who": 6, "sell_date": null, "is_borrowed": false, "camera_model": 10, "sn": "", "date": "2011-05-25T15:10:30", "sell_reason": ""}}, {"pk": 11, "model": "camera.catalog", "fields": {"comment": null, "status": "o", "given": false, "working": "maybe", "gift": true, "sell_price": 0, "price": 0, "who": 3, "sell_date": null, "is_borrowed": false, "camera_model": 11, "sn": "", "date": "2011-05-25T15:10:30", "sell_reason": ""}}, {"pk": 12, "model": "camera.catalog", "fields": {"comment": "", "status": "o", "given": false, "working": "Y", "gift": false, "sell_price": 0, "price": 250, "who": 6, "sell_date": null, "is_borrowed": false, "camera_model": 12, "sn": "314993", "date": "2011-05-25T15:10:30", "sell_reason": ""}}, {"pk": 13, "model": "camera.catalog", "fields": {"comment": "", "status": "o", "given": false, "working": "M", "gift": false, "sell_price": 0, "price": 30, "who": 6, "sell_date": null, "is_borrowed": false, "camera_model": 13, "sn": "829062", "date": "2011-05-25T15:10:30", "sell_reason": ""}}, {"pk": 14, "model": "camera.catalog", "fields": {"comment": "pere de teuf", "status": "o", "given": false, "working": "M", "gift": false, "sell_price": 0, "price": 50, "who": 6, "sell_date": null, "is_borrowed": false, "camera_model": 14, "sn": "1046553", "date": "2011-05-25T15:10:30", "sell_reason": ""}}, {"pk": 15, "model": "camera.catalog", "fields": {"comment": "pb de pille", "status": "o", "given": true, "working": "Y", "gift": false, "sell_price": 0, "price": 0, "who": 5, "sell_date": null, "is_borrowed": false, "camera_model": 15, "sn": "1179380", "date": "2011-05-25T15:10:30", "sell_reason": ""}}, {"pk": 16, "model": "camera.catalog", "fields": {"comment": "", "status": "o", "given": true, "working": "Y", "gift": false, "sell_price": 0, "price": 0, "who": 2, "sell_date": null, "is_borrowed": false, "camera_model": 16, "sn": "676193", "date": "2011-05-25T15:10:31", "sell_reason": ""}}, {"pk": 17, "model": "camera.catalog", "fields": {"comment": "pb declancheur", "status": "o", "given": true, "working": "M", "gift": false, "sell_price": 0, "price": 0, "who": 4, "sell_date": null, "is_borrowed": false, "camera_model": 29, "sn": "5881289", "date": "2011-05-25T15:10:31", "sell_reason": ""}}, {"pk": 18, "model": "camera.catalog", "fields": {"comment": "rendu a Patricia", "status": "o", "given": false, "working": "Y", "gift": false, "sell_price": 0, "price": 0, "who": 1, "sell_date": null, "is_borrowed": true, "camera_model": 17, "sn": "", "date": "2011-05-25T15:10:31", "sell_reason": ""}}, {"pk": 19, "model": "camera.catalog", "fields": {"comment": "", "status": "o", "given": false, "working": "Y", "gift": false, "sell_price": 0, "price": 40, "who": 6, "sell_date": null, "is_borrowed": false, "camera_model": 18, "sn": "", "date": "2011-05-25T15:10:31", "sell_reason": ""}}, {"pk": 20, "model": "camera.catalog", "fields": {"comment": null, "status": "o", "given": false, "working": "maybe", "gift": false, "sell_price": 0, "price": 30, "who": 6, "sell_date": null, "is_borrowed": false, "camera_model": 19, "sn": "", "date": "2011-05-25T15:10:31", "sell_reason": ""}}, {"pk": 21, "model": "camera.catalog", "fields": {"comment": "en cours de destruction", "status": "o", "given": false, "working": "N", "gift": false, "sell_price": 0, "price": 10, "who": 6, "sell_date": null, "is_borrowed": false, "camera_model": 20, "sn": "", "date": "2011-05-25T15:10:31", "sell_reason": ""}}, {"pk": 22, "model": "camera.catalog", "fields": {"comment": "", "status": "o", "given": true, "working": "Y", "gift": false, "sell_price": 0, "price": 0, "who": 3, "sell_date": null, "is_borrowed": false, "camera_model": 21, "sn": "103525", "date": "2011-05-25T15:10:31", "sell_reason": ""}}, {"pk": 23, "model": "camera.catalog", "fields": {"comment": null, "status": "o", "given": false, "working": "maybe", "gift": false, "sell_price": 0, "price": 35, "who": 6, "sell_date": null, "is_borrowed": false, "camera_model": 30, "sn": "5464876", "date": "2011-05-25T15:10:31", "sell_reason": ""}}, {"pk": 24, "model": "camera.catalog", "fields": {"comment": "", "status": "o", "given": false, "working": "Y", "gift": false, "sell_price": 0, "price": 10, "who": 6, "sell_date": null, "is_borrowed": false, "camera_model": 22, "sn": "k171181", "date": "2011-05-25T15:10:31", "sell_reason": ""}}, {"pk": 25, "model": "camera.catalog", "fields": {"comment": "", "status": "o", "given": true, "working": "M", "gift": false, "sell_price": 0, "price": 0, "who": 4, "sell_date": null, "is_borrowed": false, "camera_model": 23, "sn": "906231", "date": "2011-05-25T15:10:32", "sell_reason": ""}}, {"pk": 26, "model": "camera.catalog", "fields": {"comment": null, "status": "o", "given": false, "working": "maybe", "gift": false, "sell_price": 0, "price": 30, "who": 6, "sell_date": null, "is_borrowed": false, "camera_model": 31, "sn": "8110930", "date": "2011-05-25T15:10:32", "sell_reason": ""}}, {"pk": 27, "model": "camera.catalog", "fields": {"comment": "", "status": "o", "given": true, "working": "Y", "gift": false, "sell_price": 0, "price": 0, "who": 3, "sell_date": null, "is_borrowed": false, "camera_model": 24, "sn": "", "date": "2011-05-25T15:10:32", "sell_reason": ""}}, {"pk": 28, "model": "camera.catalog", "fields": {"comment": "", "status": "o", "given": false, "working": "L", "gift": false, "sell_price": 0, "price": 60, "who": 6, "sell_date": null, "is_borrowed": false, "camera_model": 25, "sn": "", "date": "2011-05-25T15:10:32", "sell_reason": ""}}, {"pk": 29, "model": "camera.catalog", "fields": {"comment": "", "status": "o", "given": false, "working": "N", "gift": false, "sell_price": 0, "price": 45, "who": 6, "sell_date": null, "is_borrowed": false, "camera_model": 26, "sn": "1167658", "date": "2011-05-25T15:10:32", "sell_reason": ""}}, {"pk": 30, "model": "camera.catalog", "fields": {"comment": null, "status": "o", "given": false, "working": "maybe", "gift": false, "sell_price": 0, "price": 15, "who": 6, "sell_date": null, "is_borrowed": false, "camera_model": 27, "sn": "", "date": "2011-05-25T15:10:32", "sell_reason": ""}}, {"pk": 31, "model": "camera.catalog", "fields": {"comment": "", "status": "o", "given": false, "working": "M", "gift": false, "sell_price": 0, "price": 50, "who": 6, "sell_date": null, "is_borrowed": false, "camera_model": 28, "sn": "212861", "date": "2011-05-25T15:10:32", "sell_reason": ""}}, {"pk": 35, "model": "camera.catalog", "fields": {"comment": "falsly sold as a F3 HP", "status": "o", "given": false, "working": "Y", "gift": false, "sell_price": 0, "price": 200, "who": 6, "sell_date": null, "is_borrowed": false, "camera_model": 33, "sn": "1326428", "date": "2011-06-05T13:34:37", "sell_reason": ""}}, {"pk": 36, "model": "camera.catalog", "fields": {"comment": "", "status": "o", "given": false, "working": "Y", "gift": false, "sell_price": 0, "price": 30, "who": 6, "sell_date": null, "is_borrowed": false, "camera_model": 34, "sn": "30600344", "date": "2011-06-05T13:35:55", "sell_reason": ""}}, {"pk": 38, "model": "camera.catalog", "fields": {"comment": "fonctionne apres avoir pass\u00e9 le rideau \u00e0 l'encre de chine", "status": "o", "given": false, "working": "Y", "gift": false, "sell_price": 0, "price": 40, "who": 6, "sell_date": null, "is_borrowed": false, "camera_model": 35, "sn": "351213", "date": "2011-01-12T15:08:20", "sell_reason": ""}}, {"pk": 39, "model": "camera.catalog", "fields": {"comment": "from russia (teuf)", "status": "o", "given": false, "working": "Y", "gift": false, "sell_price": 0, "price": 40, "who": 6, "sell_date": null, "is_borrowed": false, "camera_model": 36, "sn": "5565960", "date": "2011-03-27T16:35:53", "sell_reason": ""}}, {"pk": 40, "model": "camera.catalog", "fields": {"comment": "from russia (teuf)", "status": "o", "given": false, "working": "M", "gift": false, "sell_price": 0, "price": 40, "who": 6, "sell_date": null, "is_borrowed": false, "camera_model": 37, "sn": "448041", "date": "2011-03-27T16:36:22", "sell_reason": ""}}, {"pk": 41, "model": "camera.catalog", "fields": {"comment": "fake Golden Leica", "status": "o", "given": false, "working": "maybe", "gift": false, "sell_price": 0, "price": 120, "who": 6, "sell_date": null, "is_borrowed": false, "camera_model": 38, "sn": "", "date": "2011-03-27T16:37:14", "sell_reason": ""}}, {"pk": 42, "model": "camera.catalog", "fields": {"comment": "", "status": "o", "given": false, "working": "M", "gift": false, "sell_price": 0, "price": 10, "who": 6, "sell_date": null, "is_borrowed": false, "camera_model": 39, "sn": "513741", "date": "2011-03-27T16:40:13", "sell_reason": ""}}, {"pk": 43, "model": "camera.catalog", "fields": {"comment": "", "status": "o", "given": false, "working": "M", "gift": false, "sell_price": 0, "price": 30, "who": 6, "sell_date": null, "is_borrowed": false, "camera_model": 40, "sn": "FE3074830", "date": "2011-03-11T16:40:26", "sell_reason": ""}}, {"pk": 44, "model": "camera.catalog", "fields": {"comment": "from Russia (en cours de demontage)", "status": "o", "given": false, "working": "N", "gift": false, "sell_price": 0, "price": 30, "who": 6, "sell_date": null, "is_borrowed": false, "camera_model": 41, "sn": "70169467", "date": "2011-03-27T16:40:58", "sell_reason": ""}}, {"pk": 45, "model": "camera.catalog", "fields": {"comment": "", "status": "o", "given": false, "working": "L", "gift": false, "sell_price": 0, "price": 10, "who": 6, "sell_date": null, "is_borrowed": false, "camera_model": 41, "sn": "72253149", "date": "2011-03-27T16:41:11", "sell_reason": ""}}, {"pk": 46, "model": "camera.catalog", "fields": {"comment": "avec manuel papier", "status": "o", "given": false, "working": "Y", "gift": false, "sell_price": 0, "price": 100, "who": 6, "sell_date": null, "is_borrowed": false, "camera_model": 42, "sn": "592298", "date": "2012-03-11T18:36:11", "sell_reason": ""}}, {"pk": 47, "model": "camera.catalog", "fields": {"comment": "from russia - teuf", "status": "o", "given": false, "working": "M", "gift": false, "sell_price": 0, "price": 40, "who": 6, "sell_date": null, "is_borrowed": false, "camera_model": 36, "sn": "5537843", "date": "2012-05-04T13:46:07", "sell_reason": ""}}, {"pk": 48, "model": "camera.catalog", "fields": {"comment": "pas de verre depoli ni de prisme ni de cache MD", "status": "o", "given": false, "working": "N", "gift": false, "sell_price": 0, "price": 20, "who": 6, "sell_date": null, "is_borrowed": false, "camera_model": 33, "sn": "1475039", "date": "2012-06-02T16:00:00", "sell_reason": ""}}, {"pk": 49, "model": "camera.catalog", "fields": {"comment": "appareil au pere de manu S", "status": "o", "given": false, "working": "Y", "gift": false, "sell_price": 0, "price": 65, "who": 6, "sell_date": null, "is_borrowed": false, "camera_model": 43, "sn": "270119", "date": "2012-06-12T18:30:00", "sell_reason": ""}}, {"pk": 50, "model": "camera.catalog", "fields": {"comment": "", "status": "o", "given": false, "working": "M", "gift": false, "sell_price": 0, "price": 15, "who": 6, "sell_date": null, "is_borrowed": false, "camera_model": 44, "sn": "540560", "date": "2012-06-12T18:30:00", "sell_reason": ""}}, {"pk": 51, "model": "camera.catalog", "fields": {"comment": "double reglage focus", "status": "o", "given": false, "working": "M", "gift": false, "sell_price": 0, "price": 58, "who": 6, "sell_date": null, "is_borrowed": false, "camera_model": 45, "sn": "53.505 B", "date": "2013-03-17T14:39:14", "sell_reason": ""}}, {"pk": 52, "model": "camera.catalog", "fields": {"comment": "", "status": "o", "given": false, "working": "Y", "gift": false, "sell_price": 0, "price": 30, "who": 6, "sell_date": null, "is_borrowed": false, "camera_model": 46, "sn": "177094", "date": "2013-03-17T14:41:10", "sell_reason": ""}}, {"pk": 53, "model": "camera.catalog", "fields": {"comment": "", "status": "s", "given": false, "working": "Y", "gift": false, "sell_price": 380, "price": 380, "who": 6, "sell_date": "2013-04-06T16:41:02", "is_borrowed": false, "camera_model": 47, "sn": "00105812", "date": "2013-03-17T14:42:32", "sell_reason": "Rembours\u00e9 par le vendeur (http://www.photocine-gobelins.com/) parce que le produit n'etait pas celui vendu (vendu comme un Bessa R2)."}}]
